tononkira/__init__.py
tononkira/tononkira.py
tononkira-1.1.0.data/scripts/tononkira
tononkira-1.1.0.data/scripts/tononkira.bat
tononkira-1.1.0.dist-info/LICENSE
tononkira-1.1.0.dist-info/METADATA
tononkira-1.1.0.dist-info/WHEEL
tononkira-1.1.0.dist-info/top_level.txt
tononkira-1.1.0.dist-info/RECORD
