Metadata-Version: 2.1
Name: tononkira
Version: 1.1.0
Summary: Unofficial Module and CLI tool to get Malagasy song lyrics from https://tononkira.serasera.org
Home-page: https://github.com/gaetan1903/tononkira
Author: iTeam-$
Author-email: gaetan@iteam-s.mg
License: UNKNOWN
Project-URL: Bug Tracker, https://github.com/gaetan1903/tononkira/issues
Platform: UNKNOWN
Classifier: Programming Language :: Python :: 3
Classifier: Programming Language :: Python :: 3.6
Classifier: Programming Language :: Python :: 3.7
Classifier: Programming Language :: Python :: 3.8
Classifier: Programming Language :: Python :: 3.9
Classifier: Programming Language :: Python :: 3.10
Classifier: Programming Language :: Python :: 3.11
Classifier: License :: OSI Approved :: MIT License
Classifier: Operating System :: OS Independent
Requires-Python: >=3.6
License-File: LICENSE
Requires-Dist: beautifulSoup4
Requires-Dist: requests
